cryptraider/__init__.py
cryptraider/cipher/__init__.py
cryptraider/cipher/ecb_chosen_prefix.py
cryptraider/derand/__init__.py
cryptraider/derand/mersenne.py
cryptraider/math/__init__.py
cryptraider/math/mod_algorithms.py
tests/__init__.py
tests/context.py
tests/cipher/__init__.py
tests/cipher/test_ecb_chosen_prefix.py
tests/derand/__init__.py
tests/derand/test_derand.py
tests/math/__init__.py
tests/math/test_mod_algorithms.py
cryptraider-0.0.1.dist-info/LICENSE
cryptraider-0.0.1.dist-info/METADATA
cryptraider-0.0.1.dist-info/WHEEL
cryptraider-0.0.1.dist-info/top_level.txt
cryptraider-0.0.1.dist-info/RECORD
